{"v":4,"entries":{"shared-banner--black":{"type":"story","id":"shared-banner--black","name":"Black","title":"Shared/Banner","importPath":"./src/shared/ui/Banner/index.stories.ts","tags":["story"]},"shared-banner--transparent":{"type":"story","id":"shared-banner--transparent","name":"Transparent","title":"Shared/Banner","importPath":"./src/shared/ui/Banner/index.stories.ts","tags":["story"]},"shared-button--black":{"type":"story","id":"shared-button--black","name":"Black","title":"Shared/Button","importPath":"./src/shared/ui/Button/index.stories.ts","tags":["story"]},"shared-button--transparent":{"type":"story","id":"shared-button--transparent","name":"Transparent","title":"Shared/Button","importPath":"./src/shared/ui/Button/index.stories.ts","tags":["story"]},"shared-text--default":{"type":"story","id":"shared-text--default","name":"Default","title":"Shared/Text","importPath":"./src/shared/ui/Text/index.stories.ts","tags":["story"]},"shared-text--gold":{"type":"story","id":"shared-text--gold","name":"Gold","title":"Shared/Text","importPath":"./src/shared/ui/Text/index.stories.ts","tags":["story"]},"shared-text--gold-gradient":{"type":"story","id":"shared-text--gold-gradient","name":"Gold Gradient","title":"Shared/Text","importPath":"./src/shared/ui/Text/index.stories.ts","tags":["story"]},"shared-text--black-gradient":{"type":"story","id":"shared-text--black-gradient","name":"Black Gradient","title":"Shared/Text","importPath":"./src/shared/ui/Text/index.stories.ts","tags":["story"]},"shared-text--size-m":{"type":"story","id":"shared-text--size-m","name":"Size M","title":"Shared/Text","importPath":"./src/shared/ui/Text/index.stories.ts","tags":["story"]},"shared-text--size-l":{"type":"story","id":"shared-text--size-l","name":"Size L","title":"Shared/Text","importPath":"./src/shared/ui/Text/index.stories.ts","tags":["story"]},"shared-text--size-xl":{"type":"story","id":"shared-text--size-xl","name":"Size XL","title":"Shared/Text","importPath":"./src/shared/ui/Text/index.stories.ts","tags":["story"]},"widgets-bannerwatcher--primary":{"type":"story","id":"widgets-bannerwatcher--primary","name":"Primary","title":"Widgets/BannerWatcher","importPath":"./src/widgets/BannerWatcher/ui/index.stories.ts","tags":["story"]}}}
