{"v":3,"stories":{"shared-banner--black":{"id":"shared-banner--black","name":"Black","title":"Shared/Banner","importPath":"./src/shared/ui/Banner/index.stories.ts","tags":["story"],"kind":"Shared/Banner","story":"Black","parameters":{"__id":"shared-banner--black","docsOnly":false,"fileName":"./src/shared/ui/Banner/index.stories.ts"}},"shared-banner--transparent":{"id":"shared-banner--transparent","name":"Transparent","title":"Shared/Banner","importPath":"./src/shared/ui/Banner/index.stories.ts","tags":["story"],"kind":"Shared/Banner","story":"Transparent","parameters":{"__id":"shared-banner--transparent","docsOnly":false,"fileName":"./src/shared/ui/Banner/index.stories.ts"}},"shared-button--black":{"id":"shared-button--black","name":"Black","title":"Shared/Button","importPath":"./src/shared/ui/Button/index.stories.ts","tags":["story"],"kind":"Shared/Button","story":"Black","parameters":{"__id":"shared-button--black","docsOnly":false,"fileName":"./src/shared/ui/Button/index.stories.ts"}},"shared-button--transparent":{"id":"shared-button--transparent","name":"Transparent","title":"Shared/Button","importPath":"./src/shared/ui/Button/index.stories.ts","tags":["story"],"kind":"Shared/Button","story":"Transparent","parameters":{"__id":"shared-button--transparent","docsOnly":false,"fileName":"./src/shared/ui/Button/index.stories.ts"}},"shared-text--default":{"id":"shared-text--default","name":"Default","title":"Shared/Text","importPath":"./src/shared/ui/Text/index.stories.ts","tags":["story"],"kind":"Shared/Text","story":"Default","parameters":{"__id":"shared-text--default","docsOnly":false,"fileName":"./src/shared/ui/Text/index.stories.ts"}},"shared-text--gold":{"id":"shared-text--gold","name":"Gold","title":"Shared/Text","importPath":"./src/shared/ui/Text/index.stories.ts","tags":["story"],"kind":"Shared/Text","story":"Gold","parameters":{"__id":"shared-text--gold","docsOnly":false,"fileName":"./src/shared/ui/Text/index.stories.ts"}},"shared-text--gold-gradient":{"id":"shared-text--gold-gradient","name":"Gold Gradient","title":"Shared/Text","importPath":"./src/shared/ui/Text/index.stories.ts","tags":["story"],"kind":"Shared/Text","story":"Gold Gradient","parameters":{"__id":"shared-text--gold-gradient","docsOnly":false,"fileName":"./src/shared/ui/Text/index.stories.ts"}},"shared-text--black-gradient":{"id":"shared-text--black-gradient","name":"Black Gradient","title":"Shared/Text","importPath":"./src/shared/ui/Text/index.stories.ts","tags":["story"],"kind":"Shared/Text","story":"Black Gradient","parameters":{"__id":"shared-text--black-gradient","docsOnly":false,"fileName":"./src/shared/ui/Text/index.stories.ts"}},"shared-text--size-m":{"id":"shared-text--size-m","name":"Size M","title":"Shared/Text","importPath":"./src/shared/ui/Text/index.stories.ts","tags":["story"],"kind":"Shared/Text","story":"Size M","parameters":{"__id":"shared-text--size-m","docsOnly":false,"fileName":"./src/shared/ui/Text/index.stories.ts"}},"shared-text--size-l":{"id":"shared-text--size-l","name":"Size L","title":"Shared/Text","importPath":"./src/shared/ui/Text/index.stories.ts","tags":["story"],"kind":"Shared/Text","story":"Size L","parameters":{"__id":"shared-text--size-l","docsOnly":false,"fileName":"./src/shared/ui/Text/index.stories.ts"}},"shared-text--size-xl":{"id":"shared-text--size-xl","name":"Size XL","title":"Shared/Text","importPath":"./src/shared/ui/Text/index.stories.ts","tags":["story"],"kind":"Shared/Text","story":"Size XL","parameters":{"__id":"shared-text--size-xl","docsOnly":false,"fileName":"./src/shared/ui/Text/index.stories.ts"}},"widgets-bannerwatcher--primary":{"id":"widgets-bannerwatcher--primary","name":"Primary","title":"Widgets/BannerWatcher","importPath":"./src/widgets/BannerWatcher/ui/index.stories.ts","tags":["story"],"kind":"Widgets/BannerWatcher","story":"Primary","parameters":{"__id":"widgets-bannerwatcher--primary","docsOnly":false,"fileName":"./src/widgets/BannerWatcher/ui/index.stories.ts"}}}}
